{
  "frames": {
    "teleport16.png": {
      "frame": {
        "x": 5,
        "y": 5,
        "w": 1152,
        "h": 1152
      },
      "rotated": false,
      "trimmed": false,
      "spriteSourceSize": {
        "x": 0,
        "y": 0,
        "w": 1152,
        "h": 1152
      },
      "sourceSize": {
        "w": 1152,
        "h": 1152
      },
      "pivot": {
        "x": 0.5,
        "y": 0.5
      }
    },
    "teleport24.png": {
      "frame": {
        "x": 1167,
        "y": 5,
        "w": 351,
        "h": 486
      },
      "rotated": false,
      "trimmed": false,
      "spriteSourceSize": {
        "x": 657,
        "y": 495,
        "w": 351,
        "h": 486
      },
      "sourceSize": {
        "w": 1152,
        "h": 1152
      },
      "pivot": {
        "x": 0.5,
        "y": 0.5
      }
    },
    "teleport25.png": {
      "frame": {
        "x": 1167,
        "y": 501,
        "w": 351,
        "h": 486
      },
      "rotated": false,
      "trimmed": false,
      "spriteSourceSize": {
        "x": 657,
        "y": 495,
        "w": 351,
        "h": 486
      },
      "sourceSize": {
        "w": 1152,
        "h": 1152
      },
      "pivot": {
        "x": 0.5,
        "y": 0.5
      }
    },
    "teleport6.png": {
      "frame": {
        "x": 1167,
        "y": 997,
        "w": 351,
        "h": 486
      },
      "rotated": false,
      "trimmed": false,
      "spriteSourceSize": {
        "x": 144,
        "y": 495,
        "w": 351,
        "h": 486
      },
      "sourceSize": {
        "w": 1152,
        "h": 1152
      },
      "pivot": {
        "x": 0.5,
        "y": 0.5
      }
    },
    "teleport7.png": {
      "frame": {
        "x": 5,
        "y": 1167,
        "w": 351,
        "h": 486
      },
      "rotated": false,
      "trimmed": false,
      "spriteSourceSize": {
        "x": 144,
        "y": 495,
        "w": 351,
        "h": 486
      },
      "sourceSize": {
        "w": 1152,
        "h": 1152
      },
      "pivot": {
        "x": 0.5,
        "y": 0.5
      }
    },
    "teleport23.png": {
      "frame": {
        "x": 366,
        "y": 1167,
        "w": 306,
        "h": 450
      },
      "rotated": false,
      "trimmed": false,
      "spriteSourceSize": {
        "x": 684,
        "y": 495,
        "w": 306,
        "h": 450
      },
      "sourceSize": {
        "w": 1152,
        "h": 1152
      },
      "pivot": {
        "x": 0.5,
        "y": 0.5
      }
    },
    "teleport9.png": {
      "frame": {
        "x": 682,
        "y": 1167,
        "w": 306,
        "h": 450
      },
      "rotated": false,
      "trimmed": false,
      "spriteSourceSize": {
        "x": 162,
        "y": 495,
        "w": 306,
        "h": 450
      },
      "sourceSize": {
        "w": 1152,
        "h": 1152
      },
      "pivot": {
        "x": 0.5,
        "y": 0.5
      }
    },
    "teleport27.png": {
      "frame": {
        "x": 1528,
        "y": 5,
        "w": 297,
        "h": 432
      },
      "rotated": false,
      "trimmed": false,
      "spriteSourceSize": {
        "x": 693,
        "y": 513,
        "w": 297,
        "h": 432
      },
      "sourceSize": {
        "w": 1152,
        "h": 1152
      },
      "pivot": {
        "x": 0.5,
        "y": 0.5
      }
    },
    "teleport5.png": {
      "frame": {
        "x": 1528,
        "y": 447,
        "w": 297,
        "h": 432
      },
      "rotated": false,
      "trimmed": false,
      "spriteSourceSize": {
        "x": 162,
        "y": 513,
        "w": 297,
        "h": 432
      },
      "sourceSize": {
        "w": 1152,
        "h": 1152
      },
      "pivot": {
        "x": 0.5,
        "y": 0.5
      }
    },
    "teleport28.png": {
      "frame": {
        "x": 1528,
        "y": 889,
        "w": 297,
        "h": 414
      },
      "rotated": false,
      "trimmed": false,
      "spriteSourceSize": {
        "x": 693,
        "y": 531,
        "w": 297,
        "h": 414
      },
      "sourceSize": {
        "w": 1152,
        "h": 1152
      },
      "pivot": {
        "x": 0.5,
        "y": 0.5
      }
    },
    "teleport4.png": {
      "frame": {
        "x": 1835,
        "y": 5,
        "w": 297,
        "h": 414
      },
      "rotated": false,
      "trimmed": false,
      "spriteSourceSize": {
        "x": 162,
        "y": 531,
        "w": 297,
        "h": 414
      },
      "sourceSize": {
        "w": 1152,
        "h": 1152
      },
      "pivot": {
        "x": 0.5,
        "y": 0.5
      }
    },
    "teleport10.png": {
      "frame": {
        "x": 2142,
        "y": 5,
        "w": 306,
        "h": 405
      },
      "rotated": false,
      "trimmed": false,
      "spriteSourceSize": {
        "x": 162,
        "y": 522,
        "w": 306,
        "h": 405
      },
      "sourceSize": {
        "w": 1152,
        "h": 1152
      },
      "pivot": {
        "x": 0.5,
        "y": 0.5
      }
    },
    "teleport22.png": {
      "frame": {
        "x": 2142,
        "y": 420,
        "w": 306,
        "h": 405
      },
      "rotated": false,
      "trimmed": false,
      "spriteSourceSize": {
        "x": 684,
        "y": 522,
        "w": 306,
        "h": 405
      },
      "sourceSize": {
        "w": 1152,
        "h": 1152
      },
      "pivot": {
        "x": 0.5,
        "y": 0.5
      }
    },
    "teleport11.png": {
      "frame": {
        "x": 1835,
        "y": 429,
        "w": 252,
        "h": 369
      },
      "rotated": false,
      "trimmed": false,
      "spriteSourceSize": {
        "x": 189,
        "y": 549,
        "w": 252,
        "h": 369
      },
      "sourceSize": {
        "w": 1152,
        "h": 1152
      },
      "pivot": {
        "x": 0.5,
        "y": 0.5
      }
    },
    "teleport21.png": {
      "frame": {
        "x": 1835,
        "y": 808,
        "w": 252,
        "h": 369
      },
      "rotated": false,
      "trimmed": false,
      "spriteSourceSize": {
        "x": 711,
        "y": 549,
        "w": 252,
        "h": 369
      },
      "sourceSize": {
        "w": 1152,
        "h": 1152
      },
      "pivot": {
        "x": 0.5,
        "y": 0.5
      }
    },
    "teleport29.png": {
      "frame": {
        "x": 2097,
        "y": 835,
        "w": 297,
        "h": 369
      },
      "rotated": false,
      "trimmed": false,
      "spriteSourceSize": {
        "x": 693,
        "y": 549,
        "w": 297,
        "h": 369
      },
      "sourceSize": {
        "w": 1152,
        "h": 1152
      },
      "pivot": {
        "x": 0.5,
        "y": 0.5
      }
    },
    "teleport3.png": {
      "frame": {
        "x": 1835,
        "y": 1214,
        "w": 297,
        "h": 369
      },
      "rotated": false,
      "trimmed": false,
      "spriteSourceSize": {
        "x": 162,
        "y": 549,
        "w": 297,
        "h": 369
      },
      "sourceSize": {
        "w": 1152,
        "h": 1152
      },
      "pivot": {
        "x": 0.5,
        "y": 0.5
      }
    },
    "teleport14.png": {
      "frame": {
        "x": 2097,
        "y": 429,
        "w": 27,
        "h": 351
      },
      "rotated": false,
      "trimmed": false,
      "spriteSourceSize": {
        "x": 306,
        "y": 360,
        "w": 27,
        "h": 351
      },
      "sourceSize": {
        "w": 1152,
        "h": 1152
      },
      "pivot": {
        "x": 0.5,
        "y": 0.5
      }
    },
    "teleport19.png": {
      "frame": {
        "x": 2404,
        "y": 835,
        "w": 27,
        "h": 351
      },
      "rotated": false,
      "trimmed": false,
      "spriteSourceSize": {
        "x": 819,
        "y": 360,
        "w": 27,
        "h": 351
      },
      "sourceSize": {
        "w": 1152,
        "h": 1152
      },
      "pivot": {
        "x": 0.5,
        "y": 0.5
      }
    },
    "teleport15.png": {
      "frame": {
        "x": 1528,
        "y": 1313,
        "w": 27,
        "h": 333
      },
      "rotated": false,
      "trimmed": false,
      "spriteSourceSize": {
        "x": 306,
        "y": 0,
        "w": 27,
        "h": 333
      },
      "sourceSize": {
        "w": 1152,
        "h": 1152
      },
      "pivot": {
        "x": 0.5,
        "y": 0.5
      }
    },
    "teleport18.png": {
      "frame": {
        "x": 1565,
        "y": 1313,
        "w": 27,
        "h": 333
      },
      "rotated": false,
      "trimmed": false,
      "spriteSourceSize": {
        "x": 819,
        "y": 0,
        "w": 27,
        "h": 333
      },
      "sourceSize": {
        "w": 1152,
        "h": 1152
      },
      "pivot": {
        "x": 0.5,
        "y": 0.5
      }
    },
    "walk_up3.png": {
      "frame": {
        "x": 1602,
        "y": 1313,
        "w": 189,
        "h": 324
      },
      "rotated": false,
      "trimmed": true,
      "spriteSourceSize": {
        "x": 198,
        "y": 144,
        "w": 189,
        "h": 324
      },
      "sourceSize": {
        "w": 576,
        "h": 576
      },
      "pivot": {
        "x": 0.5,
        "y": 0.5
      }
    },
    "walk_up7.png": {
      "frame": {
        "x": 2142,
        "y": 1214,
        "w": 189,
        "h": 324
      },
      "rotated": false,
      "trimmed": true,
      "spriteSourceSize": {
        "x": 198,
        "y": 144,
        "w": 189,
        "h": 324
      },
      "sourceSize": {
        "w": 576,
        "h": 576
      },
      "pivot": {
        "x": 0.5,
        "y": 0.5
      }
    },
    "teleport2.png": {
      "frame": {
        "x": 5,
        "y": 1663,
        "w": 252,
        "h": 315
      },
      "rotated": false,
      "trimmed": false,
      "spriteSourceSize": {
        "x": 189,
        "y": 585,
        "w": 252,
        "h": 315
      },
      "sourceSize": {
        "w": 1152,
        "h": 1152
      },
      "pivot": {
        "x": 0.5,
        "y": 0.5
      }
    },
    "teleport30.png": {
      "frame": {
        "x": 267,
        "y": 1663,
        "w": 252,
        "h": 315
      },
      "rotated": false,
      "trimmed": false,
      "spriteSourceSize": {
        "x": 711,
        "y": 585,
        "w": 252,
        "h": 315
      },
      "sourceSize": {
        "w": 1152,
        "h": 1152
      },
      "pivot": {
        "x": 0.5,
        "y": 0.5
      }
    },
    "walk_down2.png": {
      "frame": {
        "x": 529,
        "y": 1656,
        "w": 189,
        "h": 315
      },
      "rotated": false,
      "trimmed": true,
      "spriteSourceSize": {
        "x": 189,
        "y": 135,
        "w": 189,
        "h": 315
      },
      "sourceSize": {
        "w": 576,
        "h": 576
      },
      "pivot": {
        "x": 0.5,
        "y": 0.5
      }
    },
    "walk_down3.png": {
      "frame": {
        "x": 728,
        "y": 1656,
        "w": 189,
        "h": 315
      },
      "rotated": false,
      "trimmed": true,
      "spriteSourceSize": {
        "x": 189,
        "y": 144,
        "w": 189,
        "h": 315
      },
      "sourceSize": {
        "w": 576,
        "h": 576
      },
      "pivot": {
        "x": 0.5,
        "y": 0.5
      }
    },
    "walk_down6.png": {
      "frame": {
        "x": 927,
        "y": 1656,
        "w": 189,
        "h": 315
      },
      "rotated": false,
      "trimmed": true,
      "spriteSourceSize": {
        "x": 189,
        "y": 135,
        "w": 189,
        "h": 315
      },
      "sourceSize": {
        "w": 576,
        "h": 576
      },
      "pivot": {
        "x": 0.5,
        "y": 0.5
      }
    },
    "walk_down7.png": {
      "frame": {
        "x": 1126,
        "y": 1656,
        "w": 189,
        "h": 315
      },
      "rotated": false,
      "trimmed": true,
      "spriteSourceSize": {
        "x": 189,
        "y": 144,
        "w": 189,
        "h": 315
      },
      "sourceSize": {
        "w": 576,
        "h": 576
      },
      "pivot": {
        "x": 0.5,
        "y": 0.5
      }
    },
    "walk_up2.png": {
      "frame": {
        "x": 1325,
        "y": 1493,
        "w": 189,
        "h": 315
      },
      "rotated": false,
      "trimmed": true,
      "spriteSourceSize": {
        "x": 198,
        "y": 135,
        "w": 189,
        "h": 315
      },
      "sourceSize": {
        "w": 576,
        "h": 576
      },
      "pivot": {
        "x": 0.5,
        "y": 0.5
      }
    },
    "walk_up6.png": {
      "frame": {
        "x": 1524,
        "y": 1656,
        "w": 189,
        "h": 315
      },
      "rotated": false,
      "trimmed": true,
      "spriteSourceSize": {
        "x": 198,
        "y": 135,
        "w": 189,
        "h": 315
      },
      "sourceSize": {
        "w": 576,
        "h": 576
      },
      "pivot": {
        "x": 0.5,
        "y": 0.5
      }
    },
    "idle1.png": {
      "frame": {
        "x": 1723,
        "y": 1647,
        "w": 189,
        "h": 306
      },
      "rotated": false,
      "trimmed": true,
      "spriteSourceSize": {
        "x": 189,
        "y": 135,
        "w": 189,
        "h": 306
      },
      "sourceSize": {
        "w": 576,
        "h": 576
      },
      "pivot": {
        "x": 0.5,
        "y": 0.5
      }
    },
    "teleport1.png": {
      "frame": {
        "x": 1922,
        "y": 1593,
        "w": 189,
        "h": 306
      },
      "rotated": false,
      "trimmed": false,
      "spriteSourceSize": {
        "x": 216,
        "y": 603,
        "w": 189,
        "h": 306
      },
      "sourceSize": {
        "w": 1152,
        "h": 1152
      },
      "pivot": {
        "x": 0.5,
        "y": 0.5
      }
    },
    "teleport31.png": {
      "frame": {
        "x": 2121,
        "y": 1593,
        "w": 189,
        "h": 306
      },
      "rotated": false,
      "trimmed": false,
      "spriteSourceSize": {
        "x": 747,
        "y": 603,
        "w": 189,
        "h": 306
      },
      "sourceSize": {
        "w": 1152,
        "h": 1152
      },
      "pivot": {
        "x": 0.5,
        "y": 0.5
      }
    },
    "walk_east1.png": {
      "frame": {
        "x": 2458,
        "y": 5,
        "w": 189,
        "h": 306
      },
      "rotated": false,
      "trimmed": true,
      "spriteSourceSize": {
        "x": 189,
        "y": 144,
        "w": 189,
        "h": 306
      },
      "sourceSize": {
        "w": 576,
        "h": 576
      },
      "pivot": {
        "x": 0.5,
        "y": 0.5
      }
    },
    "walk_east2.png": {
      "frame": {
        "x": 2458,
        "y": 321,
        "w": 189,
        "h": 306
      },
      "rotated": false,
      "trimmed": true,
      "spriteSourceSize": {
        "x": 189,
        "y": 144,
        "w": 189,
        "h": 306
      },
      "sourceSize": {
        "w": 576,
        "h": 576
      },
      "pivot": {
        "x": 0.5,
        "y": 0.5
      }
    },
    "walk_east6.png": {
      "frame": {
        "x": 2458,
        "y": 637,
        "w": 189,
        "h": 306
      },
      "rotated": false,
      "trimmed": true,
      "spriteSourceSize": {
        "x": 189,
        "y": 144,
        "w": 189,
        "h": 306
      },
      "sourceSize": {
        "w": 576,
        "h": 576
      },
      "pivot": {
        "x": 0.5,
        "y": 0.5
      }
    },
    "walk_up1.png": {
      "frame": {
        "x": 2441,
        "y": 953,
        "w": 189,
        "h": 306
      },
      "rotated": false,
      "trimmed": true,
      "spriteSourceSize": {
        "x": 198,
        "y": 135,
        "w": 189,
        "h": 306
      },
      "sourceSize": {
        "w": 576,
        "h": 576
      },
      "pivot": {
        "x": 0.5,
        "y": 0.5
      }
    },
    "walk_west1.png": {
      "frame": {
        "x": 2341,
        "y": 1269,
        "w": 189,
        "h": 306
      },
      "rotated": false,
      "trimmed": true,
      "spriteSourceSize": {
        "x": 189,
        "y": 135,
        "w": 189,
        "h": 306
      },
      "sourceSize": {
        "w": 576,
        "h": 576
      },
      "pivot": {
        "x": 0.5,
        "y": 0.5
      }
    },
    "walk_west2.png": {
      "frame": {
        "x": 2320,
        "y": 1585,
        "w": 189,
        "h": 306
      },
      "rotated": false,
      "trimmed": true,
      "spriteSourceSize": {
        "x": 189,
        "y": 135,
        "w": 189,
        "h": 306
      },
      "sourceSize": {
        "w": 576,
        "h": 576
      },
      "pivot": {
        "x": 0.5,
        "y": 0.5
      }
    },
    "walk_west6.png": {
      "frame": {
        "x": 2657,
        "y": 5,
        "w": 189,
        "h": 306
      },
      "rotated": false,
      "trimmed": true,
      "spriteSourceSize": {
        "x": 189,
        "y": 135,
        "w": 189,
        "h": 306
      },
      "sourceSize": {
        "w": 576,
        "h": 576
      },
      "pivot": {
        "x": 0.5,
        "y": 0.5
      }
    },
    "walk_east3.png": {
      "frame": {
        "x": 2657,
        "y": 321,
        "w": 189,
        "h": 297
      },
      "rotated": false,
      "trimmed": true,
      "spriteSourceSize": {
        "x": 189,
        "y": 153,
        "w": 189,
        "h": 297
      },
      "sourceSize": {
        "w": 576,
        "h": 576
      },
      "pivot": {
        "x": 0.5,
        "y": 0.5
      }
    },
    "walk_east7.png": {
      "frame": {
        "x": 2657,
        "y": 628,
        "w": 189,
        "h": 297
      },
      "rotated": false,
      "trimmed": true,
      "spriteSourceSize": {
        "x": 189,
        "y": 153,
        "w": 189,
        "h": 297
      },
      "sourceSize": {
        "w": 576,
        "h": 576
      },
      "pivot": {
        "x": 0.5,
        "y": 0.5
      }
    },
    "walk_west3.png": {
      "frame": {
        "x": 2657,
        "y": 935,
        "w": 189,
        "h": 297
      },
      "rotated": false,
      "trimmed": true,
      "spriteSourceSize": {
        "x": 189,
        "y": 144,
        "w": 189,
        "h": 297
      },
      "sourceSize": {
        "w": 576,
        "h": 576
      },
      "pivot": {
        "x": 0.5,
        "y": 0.5
      }
    },
    "walk_west7.png": {
      "frame": {
        "x": 2640,
        "y": 1242,
        "w": 189,
        "h": 297
      },
      "rotated": false,
      "trimmed": true,
      "spriteSourceSize": {
        "x": 189,
        "y": 144,
        "w": 189,
        "h": 297
      },
      "sourceSize": {
        "w": 576,
        "h": 576
      },
      "pivot": {
        "x": 0.5,
        "y": 0.5
      }
    },
    "idle2.png": {
      "frame": {
        "x": 2519,
        "y": 1585,
        "w": 189,
        "h": 288
      },
      "rotated": false,
      "trimmed": true,
      "spriteSourceSize": {
        "x": 189,
        "y": 153,
        "w": 189,
        "h": 288
      },
      "sourceSize": {
        "w": 576,
        "h": 576
      },
      "pivot": {
        "x": 0.5,
        "y": 0.5
      }
    },
    "teleport12.png": {
      "frame": {
        "x": 2540,
        "y": 1269,
        "w": 63,
        "h": 288
      },
      "rotated": false,
      "trimmed": false,
      "spriteSourceSize": {
        "x": 288,
        "y": 621,
        "w": 63,
        "h": 288
      },
      "sourceSize": {
        "w": 1152,
        "h": 1152
      },
      "pivot": {
        "x": 0.5,
        "y": 0.5
      }
    },
    "teleport13.png": {
      "frame": {
        "x": 2718,
        "y": 1549,
        "w": 63,
        "h": 270
      },
      "rotated": false,
      "trimmed": false,
      "spriteSourceSize": {
        "x": 288,
        "y": 549,
        "w": 63,
        "h": 270
      },
      "sourceSize": {
        "w": 1152,
        "h": 1152
      },
      "pivot": {
        "x": 0.5,
        "y": 0.5
      }
    },
    "teleport20.png": {
      "frame": {
        "x": 998,
        "y": 1167,
        "w": 63,
        "h": 270
      },
      "rotated": false,
      "trimmed": false,
      "spriteSourceSize": {
        "x": 801,
        "y": 549,
        "w": 63,
        "h": 270
      },
      "sourceSize": {
        "w": 1152,
        "h": 1152
      },
      "pivot": {
        "x": 0.5,
        "y": 0.5
      }
    },
    "walk_down1.png": {
      "frame": {
        "x": 1723,
        "y": 1647,
        "w": 189,
        "h": 306
      },
      "rotated": false,
      "trimmed": true,
      "spriteSourceSize": {
        "x": 189,
        "y": 135,
        "w": 189,
        "h": 306
      },
      "sourceSize": {
        "w": 576,
        "h": 576
      },
      "pivot": {
        "x": 0.5,
        "y": 0.5
      }
    },
    "walk_down5.png": {
      "frame": {
        "x": 1723,
        "y": 1647,
        "w": 189,
        "h": 306
      },
      "rotated": false,
      "trimmed": true,
      "spriteSourceSize": {
        "x": 189,
        "y": 135,
        "w": 189,
        "h": 306
      },
      "sourceSize": {
        "w": 576,
        "h": 576
      },
      "pivot": {
        "x": 0.5,
        "y": 0.5
      }
    },
    "teleport17.png": {
      "frame": {
        "x": 5,
        "y": 5,
        "w": 1152,
        "h": 1152
      },
      "rotated": false,
      "trimmed": false,
      "spriteSourceSize": {
        "x": 0,
        "y": 0,
        "w": 1152,
        "h": 1152
      },
      "sourceSize": {
        "w": 1152,
        "h": 1152
      },
      "pivot": {
        "x": 0.5,
        "y": 0.5
      }
    },
    "teleport26.png": {
      "frame": {
        "x": 1167,
        "y": 5,
        "w": 351,
        "h": 486
      },
      "rotated": false,
      "trimmed": false,
      "spriteSourceSize": {
        "x": 657,
        "y": 495,
        "w": 351,
        "h": 486
      },
      "sourceSize": {
        "w": 1152,
        "h": 1152
      },
      "pivot": {
        "x": 0.5,
        "y": 0.5
      }
    },
    "teleport8.png": {
      "frame": {
        "x": 1167,
        "y": 997,
        "w": 351,
        "h": 486
      },
      "rotated": false,
      "trimmed": false,
      "spriteSourceSize": {
        "x": 144,
        "y": 495,
        "w": 351,
        "h": 486
      },
      "sourceSize": {
        "w": 1152,
        "h": 1152
      },
      "pivot": {
        "x": 0.5,
        "y": 0.5
      }
    },
    "walk_down4.png": {
      "frame": {
        "x": 529,
        "y": 1656,
        "w": 189,
        "h": 315
      },
      "rotated": false,
      "trimmed": true,
      "spriteSourceSize": {
        "x": 189,
        "y": 135,
        "w": 189,
        "h": 315
      },
      "sourceSize": {
        "w": 576,
        "h": 576
      },
      "pivot": {
        "x": 0.5,
        "y": 0.5
      }
    },
    "walk_down8.png": {
      "frame": {
        "x": 927,
        "y": 1656,
        "w": 189,
        "h": 315
      },
      "rotated": false,
      "trimmed": true,
      "spriteSourceSize": {
        "x": 189,
        "y": 135,
        "w": 189,
        "h": 315
      },
      "sourceSize": {
        "w": 576,
        "h": 576
      },
      "pivot": {
        "x": 0.5,
        "y": 0.5
      }
    },
    "walk_east5.png": {
      "frame": {
        "x": 2458,
        "y": 5,
        "w": 189,
        "h": 306
      },
      "rotated": false,
      "trimmed": true,
      "spriteSourceSize": {
        "x": 189,
        "y": 144,
        "w": 189,
        "h": 306
      },
      "sourceSize": {
        "w": 576,
        "h": 576
      },
      "pivot": {
        "x": 0.5,
        "y": 0.5
      }
    },
    "walk_east4.png": {
      "frame": {
        "x": 2458,
        "y": 321,
        "w": 189,
        "h": 306
      },
      "rotated": false,
      "trimmed": true,
      "spriteSourceSize": {
        "x": 189,
        "y": 144,
        "w": 189,
        "h": 306
      },
      "sourceSize": {
        "w": 576,
        "h": 576
      },
      "pivot": {
        "x": 0.5,
        "y": 0.5
      }
    },
    "walk_east8.png": {
      "frame": {
        "x": 2458,
        "y": 637,
        "w": 189,
        "h": 306
      },
      "rotated": false,
      "trimmed": true,
      "spriteSourceSize": {
        "x": 189,
        "y": 144,
        "w": 189,
        "h": 306
      },
      "sourceSize": {
        "w": 576,
        "h": 576
      },
      "pivot": {
        "x": 0.5,
        "y": 0.5
      }
    },
    "walk_up5.png": {
      "frame": {
        "x": 2441,
        "y": 953,
        "w": 189,
        "h": 306
      },
      "rotated": false,
      "trimmed": true,
      "spriteSourceSize": {
        "x": 198,
        "y": 135,
        "w": 189,
        "h": 306
      },
      "sourceSize": {
        "w": 576,
        "h": 576
      },
      "pivot": {
        "x": 0.5,
        "y": 0.5
      }
    },
    "walk_up4.png": {
      "frame": {
        "x": 1325,
        "y": 1493,
        "w": 189,
        "h": 315
      },
      "rotated": false,
      "trimmed": true,
      "spriteSourceSize": {
        "x": 198,
        "y": 135,
        "w": 189,
        "h": 315
      },
      "sourceSize": {
        "w": 576,
        "h": 576
      },
      "pivot": {
        "x": 0.5,
        "y": 0.5
      }
    },
    "walk_up8.png": {
      "frame": {
        "x": 1524,
        "y": 1656,
        "w": 189,
        "h": 315
      },
      "rotated": false,
      "trimmed": true,
      "spriteSourceSize": {
        "x": 198,
        "y": 135,
        "w": 189,
        "h": 315
      },
      "sourceSize": {
        "w": 576,
        "h": 576
      },
      "pivot": {
        "x": 0.5,
        "y": 0.5
      }
    },
    "walk_west5.png": {
      "frame": {
        "x": 2341,
        "y": 1269,
        "w": 189,
        "h": 306
      },
      "rotated": false,
      "trimmed": true,
      "spriteSourceSize": {
        "x": 189,
        "y": 135,
        "w": 189,
        "h": 306
      },
      "sourceSize": {
        "w": 576,
        "h": 576
      },
      "pivot": {
        "x": 0.5,
        "y": 0.5
      }
    },
    "walk_west4.png": {
      "frame": {
        "x": 2320,
        "y": 1585,
        "w": 189,
        "h": 306
      },
      "rotated": false,
      "trimmed": true,
      "spriteSourceSize": {
        "x": 189,
        "y": 135,
        "w": 189,
        "h": 306
      },
      "sourceSize": {
        "w": 576,
        "h": 576
      },
      "pivot": {
        "x": 0.5,
        "y": 0.5
      }
    },
    "walk_west8.png": {
      "frame": {
        "x": 2657,
        "y": 5,
        "w": 189,
        "h": 306
      },
      "rotated": false,
      "trimmed": true,
      "spriteSourceSize": {
        "x": 189,
        "y": 135,
        "w": 189,
        "h": 306
      },
      "sourceSize": {
        "w": 576,
        "h": 576
      },
      "pivot": {
        "x": 0.5,
        "y": 0.5
      }
    }
  },
  "meta": {
    "app": "http://free-tex-packer.com",
    "version": "0.6.7",
    "image": "john.png",
    "format": "RGBA8888",
    "size": {
      "w": 2851,
      "h": 1983
    },
    "scale": 1
  }
}